{"is_source_file": true, "format": "TypeScript React (TSX)", "description": "This file defines a React component named ProductList that renders a list of books as cards, displaying details such as title, author, category, price, and cover image. It also includes a Book type definition and handles fallback images for missing or failed cover image loads.", "external_files": ["react", "react-router-dom"], "external_methods": ["React", "Link"], "published": ["Book"], "classes": [], "methods": [{"name": "ProductList", "description": "React functional component that renders a grid of book cards based on the provided items array."}], "calls": ["React", "Link", "window.location.origin"], "search-terms": ["ProductList", "Book", "book.imageUrl", "fallback image", "React component", "book category badge", "book description truncate", "book detail route"], "state": 2, "file_id": 17, "knowledge_revision": 108, "git_revision": "dee853f78f9c816e7b7d62911992f18fa75bd1e1", "revision_history": [{"40": "dac82a428eacdb1b0709a498927834eab4bd7f44"}, {"54": "dac82a428eacdb1b0709a498927834eab4bd7f44"}, {"65": "666ce5153c5c3ea63e4c541c884a8a0d0e9a245f"}, {"78": "671d60110a4af6bc81e5cc9fa4269e65f23eb27b"}, {"91": "67881fc5a44d18eb98c98d423c6cb6f60311e65f"}, {"102": "a64c88edbead2176a40c0e632b37421157b833c4"}, {"108": "dee853f78f9c816e7b7d62911992f18fa75bd1e1"}], "ctags": [], "hash": "81eee1b6bb8e8e763892c9ee5ba34839", "format-version": 4, "code-base-name": "bookstore_frontend", "filename": "bookstore_frontend/src/components/ProductList.tsx"}